tests/__init__.py
tests/beams/__init__.py
tests/beams/test_simply_supported.py
zandbak/__init__.py
zandbak/beams/__init__.py
zandbak/beams/simply_supported.py
zandbak-0.2.11.dist-info/LICENSE
zandbak-0.2.11.dist-info/METADATA
zandbak-0.2.11.dist-info/WHEEL
zandbak-0.2.11.dist-info/top_level.txt
zandbak-0.2.11.dist-info/RECORD
